sabatron_tryton_rpc_client/__init__.py
sabatron_tryton_rpc_client/cache.py
sabatron_tryton_rpc_client/client.py
sabatron_tryton_rpc_client/config.py
sabatron_tryton_rpc_client/jsonrpc.py
sabatron_tryton_rpc_client/test_client.py
sabatron_tryton_rpc_client-7.4.0.dist-info/licenses/LICENSE
tryton-rpc-client/__init__.py
tryton-rpc-client/cache.py
tryton-rpc-client/client.py
tryton-rpc-client/config.py
tryton-rpc-client/jsonrpc.py
tryton-rpc-client/test_client.py
sabatron_tryton_rpc_client-7.4.0.dist-info/METADATA
sabatron_tryton_rpc_client-7.4.0.dist-info/WHEEL
sabatron_tryton_rpc_client-7.4.0.dist-info/top_level.txt
sabatron_tryton_rpc_client-7.4.0.dist-info/RECORD
