Metadata-Version: 2.4
Name: sabatron_tryton_rpc_client
Version: 7.4.0
Summary: Python RPC Client for Tryton
Home-page: https://git.disroot.org/sabatron/sabatron-tryton-rpc-client
Author: mono
Author-email: monomono@disroot.org
License: GPL-3
Keywords: tryton client
Classifier: Programming Language :: Python :: 3
Classifier: License :: OSI Approved :: GNU General Public License v3 (GPLv3)
Classifier: Operating System :: OS Independent
Requires-Python: >=3.6
License-File: LICENSE
Dynamic: author
Dynamic: author-email
Dynamic: classifier
Dynamic: description
Dynamic: description-content-type
Dynamic: home-page
Dynamic: keywords
Dynamic: license
Dynamic: license-file
Dynamic: requires-python
Dynamic: summary
